jgtpy/JGTADS.py
jgtpy/JGTADSRequest.py
jgtpy/JGTBaseRequest.py
jgtpy/JGTCDS.py
jgtpy/JGTCDS.test.py
jgtpy/JGTCDSRequest.py
jgtpy/JGTCDSSvc.py
jgtpy/JGTChartConfig.py
jgtpy/JGTCloudFS.py
jgtpy/JGTConfig.py
jgtpy/JGTCore.py
jgtpy/JGTIDS.py
jgtpy/JGTIDSRequest.py
jgtpy/JGTIDSSvc.py
jgtpy/JGTImage.py
jgtpy/JGTLoader.py
jgtpy/JGTMKSG.py
jgtpy/JGTPDHelper.py
jgtpy/JGTPDSP.py
jgtpy/JGTPDSPSvc.py
jgtpy/JGTPDSRequest.py
jgtpy/__init__.py
jgtpy/__main__.py
jgtpy/adsfromcdsfile.py
jgtpy/adshelper.py
jgtpy/alligator_mouth_water.py
jgtpy/aohelper.py
jgtpy/cdscli.py
jgtpy/cli_utils.py
jgtpy/fe-formulation_of_target_variable_for_ML_in_FTS.py
jgtpy/fsserver.py
jgtpy/glyph_cli.py
jgtpy/glyph_signals_cli.py
jgtpy/glyph_summary_cli.py
jgtpy/idsserver.py
jgtpy/jgt2312.py
jgtpy/jgt_init.py
jgtpy/jgtapycli.py
jgtpy/jgtapyhelper.py
jgtpy/jgtbtetl1.py
jgtpy/jgtbtetl2.py
jgtpy/jgtcli.py
jgtpy/jgtdotenv.py
jgtpy/jgtetl.py
jgtpy/jgtflags.py
jgtpy/jgtpy_guide_for_agent.py
jgtpy/jgtpyconstants.py
jgtpy/jgtpyhelper.py
jgtpy/jgtservice.py
jgtpy/mouth_water_plotter.py
jgtpy/pds2cds.py
jgtpy/pdsclient.py
jgtpy/pto-panel-240209.py
jgtpy/pto__ao_divergence_finder.py
jgtpy/pto_ads_from_cds_cache.py
jgtpy/pto_featdim5.py
jgtpy/pto_feathelper.py
jgtpy/refacto__from_args__240714.py
jgtpy/skip_test_JGTIDS.py
jgtpy/skip_test_jgtcli.py
jgtpy/skip_test_jgtcommon.py
jgtpy/test_JGTADS.py
jgtpy/test_JGTPDSP.py
jgtpy/test_cli_utils.py
jgtpy/test_jgtos.py
jgtpy/test_jgtwslhelper.py
jgtpy/testmock_IDS.py
jgtpy/testpdsclient-cli.py
jgtpy/testpdsclient-h.py
jgtpy/testpdsclient-iprop.py
jgtpy/guide_for_llm_agents/adscli.md
jgtpy/guide_for_llm_agents/cdscli.md
jgtpy/guide_for_llm_agents/idscli.md
jgtpy/guide_for_llm_agents/index.md
jgtpy/guide_for_llm_agents/integration.md
jgtpy/guide_for_llm_agents/jgtcli.md
jgtpy/guide_for_llm_agents/jgtmksg.md
jgtpy/guide_for_llm_agents/jgtmouthwater.md
jgtpy/guide_for_llm_agents/jgtservice.md
jgtpy/guide_for_llm_agents/overview.md
jgtpy/guide_for_llm_agents/pds2cds.md
jgtpy-0.6.27.dist-info/licenses/LICENSE
jgtpy-0.6.27.dist-info/METADATA
jgtpy-0.6.27.dist-info/WHEEL
jgtpy-0.6.27.dist-info/entry_points.txt
jgtpy-0.6.27.dist-info/top_level.txt
jgtpy-0.6.27.dist-info/RECORD
