Metadata-Version: 2.4
Name: jgtpy
Version: 0.6.27
Summary: Enhanced JGTPy CDS, IDS, PDSP Services
Home-page: https://github.com/jgwill/jgtpy
Author: GUillaume Isabelle
Author-email: Guillaume Isabelle <jgi@jgwill.com>
Project-URL: Homepage, https://github.com/jgwill/jgtpy
Project-URL: Bug Tracker, https://github.com/jgwill/jgtpy/issues
Keywords: data
Classifier: Programming Language :: Python :: 3
Classifier: License :: OSI Approved :: MIT License
Classifier: Operating System :: OS Independent
Requires-Python: >=3.7
License-File: LICENSE
Requires-Dist: pandas>=0.25.1
Requires-Dist: python-dotenv>=0.19.2
Requires-Dist: jgtapy>=1.9.21
Requires-Dist: jgtutils>=1.0.24
Requires-Dist: jgtcore>=0.2.5
Requires-Dist: dropbox>=11.36.2
Requires-Dist: tlid>=0.1.15
Requires-Dist: scipy>=1.7.3
Requires-Dist: matplotlib>=3.3.1
Requires-Dist: plotly>=5.18.0
Requires-Dist: mplfinance>=0.12.10b0
Requires-Dist: panel>=1.2.3
Requires-Dist: tomli>=1.2.3
Requires-Dist: jinja2
Requires-Dist: dash
Requires-Dist: tdqm
Requires-Dist: jgtfxcon
Provides-Extra: serve
Requires-Dist: fastapi>=0.104.0; extra == "serve"
Requires-Dist: uvicorn>=0.24.0; extra == "serve"
Requires-Dist: httpx>=0.25.0; extra == "serve"
Requires-Dist: aiofiles>=23.2.1; extra == "serve"
Provides-Extra: dev-lint
Requires-Dist: flake8<3.7.0,>=3.6.0; extra == "dev-lint"
Requires-Dist: isort<4.4.0,>=4.3.4; extra == "dev-lint"
Provides-Extra: dev-test
Requires-Dist: coverage; extra == "dev-test"
Requires-Dist: pytest>=3.10; extra == "dev-test"
Provides-Extra: dev-docs
Requires-Dist: readme_renderer; extra == "dev-docs"
Requires-Dist: sphinx; extra == "dev-docs"
Requires-Dist: sphinx_rtd_theme>=0.4.0; extra == "dev-docs"
Requires-Dist: html2text>=2020.1.16; extra == "dev-docs"
Requires-Dist: html2markdown>=0.1.7; extra == "dev-docs"
Requires-Dist: twine; extra == "dev-docs"
Dynamic: author
Dynamic: home-page
Dynamic: license-file
